mongodb_url_validator/__init__.py
mongodb_url_validator-0.1.1.dist-info/METADATA
mongodb_url_validator-0.1.1.dist-info/WHEEL
mongodb_url_validator-0.1.1.dist-info/entry_points.txt
mongodb_url_validator-0.1.1.dist-info/top_level.txt
mongodb_url_validator-0.1.1.dist-info/RECORD
