Metadata-Version: 2.4
Name: mongodb-url-validator
Version: 0.1.1
Summary: A simple MongoDB URL validator
Author: Stark
Requires-Python: >=3.8
Requires-Dist: pymongo
